pythonkuma/__init__.py
pythonkuma/exceptions.py
pythonkuma/models.py
pythonkuma/py.typed
pythonkuma/update.py
pythonkuma/uptimekuma.py
pythonkuma-0.3.2.dist-info/METADATA
pythonkuma-0.3.2.dist-info/WHEEL
pythonkuma-0.3.2.dist-info/licenses/LICENSE
pythonkuma-0.3.2.dist-info/RECORD
