Metadata-Version: 2.4
Name: pythonkuma
Version: 0.3.2
Summary: Simple Python wrapper for Uptime Kuma
Project-URL: Source, https://github.com/tr4nt0r/pythonkuma
Project-URL: Documentation, https://tr4nt0r.github.io/pythonkuma
Author-email: Manfred Dennerlein Rodelo <manfred@dennerlein.name>, Jayakorn Karikan <jayakornk@gmail.com>
License-Expression: MIT
License-File: LICENSE
Classifier: Operating System :: OS Independent
Classifier: Programming Language :: Python :: 3
Requires-Python: >=3.12
Requires-Dist: aiohttp>=3.12.9
Requires-Dist: mashumaro>=3.13.1
Requires-Dist: prometheus-client>=0.21.0
